{
  "article_id": 522,
  "inner_id": 39,
  "code": "ТК РК",
  "article_number": 39,
  "title": "Перевод работника на другую работу",
  "text": "1. Переводом работника на другую работу является:\n1) изменение работы (трудовой функции) работника, то есть выполнение работы по другой должности, специальности, профессии, квалификации;\n2) поручение иной работы, при выполнении которой изменяются условия труда (размер заработной платы, режим рабочего времени и времени отдыха, льготы и другие условия), обусловленные трудовым договором;\n3) перевод в обособленное структурное подразделение работодателя;\n4) перевод в другую местность вместе с работодателем.\n2. Перевод работника на другую работу допускается с согласия работника, оформляется внесением соответствующих изменений в трудовой договор и актом работодателя, за исключением случаев, предусмотренных настоящим Кодексом.\n3. Не допускается перевод работника на другую работу при противопоказаниях для работника по состоянию здоровья, подтвержденных медицинским заключением.",
  "entities": [
    {
      "id": "BJnQvz_sre",
      "start": 3,
      "end": 48,
      "text": "Переводом работника на другую работу является",
      "group": "norm_structure",
      "label": "ГИПОТЕЗА"
    },
    {
      "id": "96UBrYDplO",
      "start": 50,
      "end": 506,
      "text": "1) изменение работы (трудовой функции) работника, то есть выполнение работы по другой должности, специальности, профессии, квалификации;\\n2) поручение иной работы, при выполнении которой изменяются условия труда (размер заработной платы, режим рабочего времени и времени отдыха, льготы и другие условия), обусловленные трудовым договором;\\n3) перевод в обособленное структурное подразделение работодателя;\\n4) перевод в другую местность вместе с работодателем",
      "group": "norm_structure",
      "label": "ДИСПОЗИЦИЯ"
    },
    {
      "id": "Gcfi3QSVmM",
      "start": 3,
      "end": 506,
      "text": "Переводом работника на другую работу является:\\n1) изменение работы (трудовой функции) работника, то есть выполнение работы по другой должности, специальности, профессии, квалификации;\\n2) поручение иной работы, при выполнении которой изменяются условия труда (размер заработной платы, режим рабочего времени и времени отдыха, льготы и другие условия), обусловленные трудовым договором;\\n3) перевод в обособленное структурное подразделение работодателя;\\n4) перевод в другую местность вместе с работодателем",
      "group": "modality",
      "label": "МОДАЛЬНОСТЬ_ИМПЕРАТИВНАЯ"
    },
    {
      "id": "_Dye86TvD1",
      "start": 3,
      "end": 506,
      "text": "Переводом работника на другую работу является:\\n1) изменение работы (трудовой функции) работника, то есть выполнение работы по другой должности, специальности, профессии, квалификации;\\n2) поручение иной работы, при выполнении которой изменяются условия труда (размер заработной платы, режим рабочего времени и времени отдыха, льготы и другие условия), обусловленные трудовым договором;\\n3) перевод в обособленное структурное подразделение работодателя;\\n4) перевод в другую местность вместе с работодателем",
      "group": "norm_types",
      "label": "НОРМА_ДЕФИНИТИВНАЯ"
    },
    {
      "id": "mBx4Sm1VZF",
      "start": 3,
      "end": 39,
      "text": "Переводом работника на другую работу",
      "group": "definitions",
      "label": "ТЕРМИН_ОПРЕДЕЛЯЕМЫЙ"
    },
    {
      "id": "QqbWa-fbTN",
      "start": 53,
      "end": 98,
      "text": "изменение работы (трудовой функции) работника",
      "group": "legal_objects",
      "label": "ОБЪЕКТ_ПОВЕДЕНИЕ"
    },
    {
      "id": "LeNNk8c8Dk",
      "start": 89,
      "end": 98,
      "text": "работника",
      "group": "legal_subject",
      "label": "СУБЪЕКТ_ФИЗЛИЦО"
    },
    {
      "id": "ictWmW1DYV",
      "start": 108,
      "end": 185,
      "text": "выполнение работы по другой должности, специальности, профессии, квалификации",
      "group": "legal_facts",
      "label": "ФАКТ_СОСТОЯНИЕ"
    },
    {
      "id": "ZlyZ20oueN",
      "start": 190,
      "end": 211,
      "text": "поручение иной работы",
      "group": "action_type",
      "label": "ДЕЙСТВИЕ_АКТИВНОЕ"
    },
    {
      "id": "_eC0x02tlR",
      "start": 213,
      "end": 260,
      "text": "при выполнении которой изменяются условия труда",
      "group": "conditions",
      "label": "УСЛОВИЕ_ЕСЛИ"
    },
    {
      "id": "gMwA7LnFLj",
      "start": 262,
      "end": 285,
      "text": "размер заработной платы",
      "group": "amounts",
      "label": "СУММА_ДЕНЬГИ"
    },
    {
      "id": "k6JZp136-M",
      "start": 328,
      "end": 334,
      "text": "льготы",
      "group": "amounts",
      "label": "СУММА_ДЕНЬГИ"
    },
    {
      "id": "eGuPtvQ3sM",
      "start": 287,
      "end": 326,
      "text": "режим рабочего времени и времени отдыха",
      "group": "legal_facts",
      "label": "ФАКТ_СОСТОЯНИЕ"
    },
    {
      "id": "-9C-39MMNh",
      "start": 354,
      "end": 367,
      "text": "обусловленные",
      "group": "purposes_principles",
      "label": "ОСНОВАНИЕ"
    },
    {
      "id": "Qz3CRvgKNf",
      "start": 368,
      "end": 386,
      "text": "трудовым договором",
      "group": "legal_objects",
      "label": "ОБЪЕКТ_ДОКУМЕНТ"
    },
    {
      "id": "Ml493GRMar",
      "start": 287,
      "end": 326,
      "text": "режим рабочего времени и времени отдыха",
      "group": "temporal",
      "label": "ВРЕМЯ_ПЕРИОД"
    },
    {
      "id": "iS0qK7qWQX",
      "start": 399,
      "end": 452,
      "text": "в обособленное структурное подразделение работодателя",
      "group": "conditions",
      "label": "УСЛОВИЕ_ГДЕ"
    },
    {
      "id": "n8205oAUBF",
      "start": 391,
      "end": 398,
      "text": "перевод",
      "group": "legal_facts",
      "label": "ФАКТ_СОСТОЯНИЕ"
    },
    {
      "id": "Hxa9hEJFkV",
      "start": 440,
      "end": 452,
      "text": "работодателя",
      "group": "legal_subject",
      "label": "СУБЪЕКТ_ФИЗЛИЦО"
    },
    {
      "id": "Hxa9hEJFkV",
      "start": 440,
      "end": 452,
      "text": "работодателя",
      "group": "legal_subject",
      "label": "СУБЪЕКТ_ЮРЛИЦО"
    },
    {
      "id": "nErY_DD4MN",
      "start": 457,
      "end": 464,
      "text": "перевод",
      "group": "legal_facts",
      "label": "ФАКТ_СОСТОЯНИЕ"
    },
    {
      "id": "fPwLxbCG9Y",
      "start": 465,
      "end": 506,
      "text": "в другую местность вместе с работодателем",
      "group": "conditions",
      "label": "УСЛОВИЕ_ГДЕ"
    },
    {
      "id": "wxuGOClB1x",
      "start": 493,
      "end": 506,
      "text": "работодателем",
      "group": "legal_subject",
      "label": "СУБЪЕКТ_ФИЗЛИЦО"
    },
    {
      "id": "wxuGOClB1x",
      "start": 493,
      "end": 506,
      "text": "работодателем",
      "group": "legal_subject",
      "label": "СУБЪЕКТ_ЮРЛИЦО"
    },
    {
      "id": "AZYE2-1TNR",
      "start": 414,
      "end": 439,
      "text": "структурное подразделение",
      "group": "definitions",
      "label": "ТЕРМИН_ОПРЕДЕЛЯЕМЫЙ"
    },
    {
      "id": "awKPSU3TiP",
      "start": 669,
      "end": 727,
      "text": "за исключением случаев, предусмотренных настоящим Кодексом",
      "group": "norm_structure",
      "label": "ГИПОТЕЗА"
    },
    {
      "id": "yF30wtD4Zp",
      "start": 511,
      "end": 667,
      "text": "Перевод работника на другую работу допускается с согласия работника, оформляется внесением соответствующих изменений в трудовой договор и актом работодателя",
      "group": "norm_structure",
      "label": "ДИСПОЗИЦИЯ"
    },
    {
      "id": "yuwZCuRiLz",
      "start": 511,
      "end": 727,
      "text": "Перевод работника на другую работу допускается с согласия работника, оформляется внесением соответствующих изменений в трудовой договор и актом работодателя, за исключением случаев, предусмотренных настоящим Кодексом",
      "group": "norm_types",
      "label": "НОРМА_УПРАВОМОЧИВАЮЩАЯ"
    },
    {
      "id": "lu4h5Cxk30",
      "start": 511,
      "end": 727,
      "text": "Перевод работника на другую работу допускается с согласия работника, оформляется внесением соответствующих изменений в трудовой договор и актом работодателя, за исключением случаев, предусмотренных настоящим Кодексом",
      "group": "modality",
      "label": "МОДАЛЬНОСТЬ_ДИСПОЗИТИВНАЯ"
    },
    {
      "id": "Gg079lZtJr",
      "start": 511,
      "end": 545,
      "text": "Перевод работника на другую работу",
      "group": "legal_facts",
      "label": "ФАКТ_СОСТОЯНИЕ"
    },
    {
      "id": "i_v5WwQeg5",
      "start": 519,
      "end": 528,
      "text": "работника",
      "group": "legal_subject",
      "label": "СУБЪЕКТ_ФИЗЛИЦО"
    },
    {
      "id": "QHpi8AoUaM",
      "start": 546,
      "end": 557,
      "text": "допускается",
      "group": "action_modality",
      "label": "ДЕЙСТВИЕ_ПРАВО"
    },
    {
      "id": "RS_EepGNRp",
      "start": 558,
      "end": 578,
      "text": "с согласия работника",
      "group": "purposes_principles",
      "label": "ОСНОВАНИЕ"
    },
    {
      "id": "fZDFXhJ8NW",
      "start": 569,
      "end": 578,
      "text": "работника",
      "group": "legal_subject",
      "label": "СУБЪЕКТ_ФИЗЛИЦО"
    },
    {
      "id": "TKX2IbyAFK",
      "start": 580,
      "end": 667,
      "text": "оформляется внесением соответствующих изменений в трудовой договор и актом работодателя",
      "group": "action_type",
      "label": "ДЕЙСТВИЕ_ПРОЦЕДУРНОЕ"
    },
    {
      "id": "AMVOqrbvNE",
      "start": 628,
      "end": 667,
      "text": "в трудовой договор и актом работодателя",
      "group": "legal_objects",
      "label": "ОБЪЕКТ_ДОКУМЕНТ"
    },
    {
      "id": "lks4NGm-4L",
      "start": 669,
      "end": 727,
      "text": "за исключением случаев, предусмотренных настоящим Кодексом",
      "group": "exceptions",
      "label": "ИСКЛЮЧЕНИЕ_ОБЩЕЕ"
    },
    {
      "id": "bUJcdsXpou",
      "start": 693,
      "end": 727,
      "text": "предусмотренных настоящим Кодексом",
      "group": "norm_types",
      "label": "НОРМА_БЛАНКЕТНАЯ"
    },
    {
      "id": "OWU--0YVgb",
      "start": 782,
      "end": 879,
      "text": "при противопоказаниях для работника по состоянию здоровья, подтвержденных медицинским заключением",
      "group": "norm_structure",
      "label": "ГИПОТЕЗА"
    },
    {
      "id": "OhvOEd0OZK",
      "start": 732,
      "end": 781,
      "text": "Не допускается перевод работника на другую работу",
      "group": "norm_structure",
      "label": "ДИСПОЗИЦИЯ"
    },
    {
      "id": "iJYnZP02mw",
      "start": 732,
      "end": 879,
      "text": "Не допускается перевод работника на другую работу при противопоказаниях для работника по состоянию здоровья, подтвержденных медицинским заключением",
      "group": "norm_types",
      "label": "НОРМА_ЗАПРЕЩАЮЩАЯ"
    },
    {
      "id": "O0ma0QzIuR",
      "start": 732,
      "end": 879,
      "text": "Не допускается перевод работника на другую работу при противопоказаниях для работника по состоянию здоровья, подтвержденных медицинским заключением",
      "group": "modality",
      "label": "МОДАЛЬНОСТЬ_ИМПЕРАТИВНАЯ"
    },
    {
      "id": "m1dhAZP_gK",
      "start": 732,
      "end": 781,
      "text": "Не допускается перевод работника на другую работу",
      "group": "action_modality",
      "label": "ДЕЙСТВИЕ_ЗАПРЕТ"
    },
    {
      "id": "iBnll2WMB3",
      "start": 747,
      "end": 781,
      "text": "перевод работника на другую работу",
      "group": "legal_facts",
      "label": "ФАКТ_СОСТОЯНИЕ"
    },
    {
      "id": "64rVor3CFs",
      "start": 747,
      "end": 781,
      "text": "перевод работника на другую работу",
      "group": "action_type",
      "label": "ДЕЙСТВИЕ_ПРОЦЕДУРНОЕ"
    },
    {
      "id": "YsVDXNzHXO",
      "start": 782,
      "end": 839,
      "text": "при противопоказаниях для работника по состоянию здоровья",
      "group": "legal_facts",
      "label": "ФАКТ_СОСТОЯНИЕ"
    },
    {
      "id": "VDXSoh4vxs",
      "start": 841,
      "end": 879,
      "text": "подтвержденных медицинским заключением",
      "group": "purposes_principles",
      "label": "ОСНОВАНИЕ"
    },
    {
      "id": "EQdyfdfwl-",
      "start": 841,
      "end": 879,
      "text": "подтвержденных медицинским заключением",
      "group": "action_type",
      "label": "ДЕЙСТВИЕ_ПРОЦЕДУРНОЕ"
    },
    {
      "id": "ptYUt-SNQ1",
      "start": 841,
      "end": 879,
      "text": "подтвержденных медицинским заключением",
      "group": "legal_objects",
      "label": "ОБЪЕКТ_ДОКУМЕНТ"
    },
    {
      "id": "i5X8r9FFnn",
      "start": 818,
      "end": 839,
      "text": "по состоянию здоровья",
      "group": "action_modality",
      "label": "ДЕЙСТВИЕ_ПРАВО"
    },
    {
      "id": "m9xsYd8Ajk",
      "start": 782,
      "end": 839,
      "text": "при противопоказаниях для работника по состоянию здоровья",
      "group": "purposes_principles",
      "label": "ОСНОВАНИЕ"
    }
  ],
  "relations": [
    {
      "id": "REL_0001",
      "from_id": "yuwZCuRiLz",
      "to_id": "QHpi8AoUaM",
      "from_text": "Перевод работника на другую работу допускается с согласия работника, оформляется внесением соответствующих изменений в трудовой договор и актом работодателя, за исключением случаев, предусмотренных настоящим Кодексом",
      "to_text": "допускается",
      "from_label": "norm_types:НОРМА_УПРАВОМОЧИВАЮЩАЯ",
      "to_label": "action_modality:ДЕЙСТВИЕ_ПРАВО",
      "relation": "УСТАНАВЛИВАЕТ_МОДАЛЬНОСТЬ",
      "source": "auto",
      "confidence": 0.95,
      "trigger_phrase": "(modality within norm span)",
      "algorithm": "ALGO_УСТ_МОД_v1",
      "expert_verdict": null,
      "expert_correction": null,
      "expert_comment": null
    },
    {
      "id": "REL_0002",
      "from_id": "lu4h5Cxk30",
      "to_id": "QHpi8AoUaM",
      "from_text": "Перевод работника на другую работу допускается с согласия работника, оформляется внесением соответствующих изменений в трудовой договор и актом работодателя, за исключением случаев, предусмотренных настоящим Кодексом",
      "to_text": "допускается",
      "from_label": "modality:МОДАЛЬНОСТЬ_ДИСПОЗИТИВНАЯ",
      "to_label": "action_modality:ДЕЙСТВИЕ_ПРАВО",
      "relation": "УСТАНАВЛИВАЕТ_МОДАЛЬНОСТЬ",
      "source": "auto",
      "confidence": 0.95,
      "trigger_phrase": "(modality within norm span)",
      "algorithm": "ALGO_УСТ_МОД_v1",
      "expert_verdict": null,
      "expert_correction": null,
      "expert_comment": null
    },
    {
      "id": "REL_0003",
      "from_id": "iJYnZP02mw",
      "to_id": "m1dhAZP_gK",
      "from_text": "Не допускается перевод работника на другую работу при противопоказаниях для работника по состоянию здоровья, подтвержденных медицинским заключением",
      "to_text": "Не допускается перевод работника на другую работу",
      "from_label": "norm_types:НОРМА_ЗАПРЕЩАЮЩАЯ",
      "to_label": "action_modality:ДЕЙСТВИЕ_ЗАПРЕТ",
      "relation": "УСТАНАВЛИВАЕТ_МОДАЛЬНОСТЬ",
      "source": "auto",
      "confidence": 0.95,
      "trigger_phrase": "(modality within norm span)",
      "algorithm": "ALGO_УСТ_МОД_v1",
      "expert_verdict": null,
      "expert_correction": null,
      "expert_comment": null
    },
    {
      "id": "REL_0004",
      "from_id": "iJYnZP02mw",
      "to_id": "i5X8r9FFnn",
      "from_text": "Не допускается перевод работника на другую работу при противопоказаниях для работника по состоянию здоровья, подтвержденных медицинским заключением",
      "to_text": "по состоянию здоровья",
      "from_label": "norm_types:НОРМА_ЗАПРЕЩАЮЩАЯ",
      "to_label": "action_modality:ДЕЙСТВИЕ_ПРАВО",
      "relation": "УСТАНАВЛИВАЕТ_МОДАЛЬНОСТЬ",
      "source": "auto",
      "confidence": 0.95,
      "trigger_phrase": "(modality within norm span)",
      "algorithm": "ALGO_УСТ_МОД_v1",
      "expert_verdict": null,
      "expert_correction": null,
      "expert_comment": null
    },
    {
      "id": "REL_0005",
      "from_id": "O0ma0QzIuR",
      "to_id": "m1dhAZP_gK",
      "from_text": "Не допускается перевод работника на другую работу при противопоказаниях для работника по состоянию здоровья, подтвержденных медицинским заключением",
      "to_text": "Не допускается перевод работника на другую работу",
      "from_label": "modality:МОДАЛЬНОСТЬ_ИМПЕРАТИВНАЯ",
      "to_label": "action_modality:ДЕЙСТВИЕ_ЗАПРЕТ",
      "relation": "УСТАНАВЛИВАЕТ_МОДАЛЬНОСТЬ",
      "source": "auto",
      "confidence": 0.95,
      "trigger_phrase": "(modality within norm span)",
      "algorithm": "ALGO_УСТ_МОД_v1",
      "expert_verdict": null,
      "expert_correction": null,
      "expert_comment": null
    },
    {
      "id": "REL_0006",
      "from_id": "O0ma0QzIuR",
      "to_id": "i5X8r9FFnn",
      "from_text": "Не допускается перевод работника на другую работу при противопоказаниях для работника по состоянию здоровья, подтвержденных медицинским заключением",
      "to_text": "по состоянию здоровья",
      "from_label": "modality:МОДАЛЬНОСТЬ_ИМПЕРАТИВНАЯ",
      "to_label": "action_modality:ДЕЙСТВИЕ_ПРАВО",
      "relation": "УСТАНАВЛИВАЕТ_МОДАЛЬНОСТЬ",
      "source": "auto",
      "confidence": 0.95,
      "trigger_phrase": "(modality within norm span)",
      "algorithm": "ALGO_УСТ_МОД_v1",
      "expert_verdict": null,
      "expert_correction": null,
      "expert_comment": null
    },
    {
      "id": "REL_0007",
      "from_id": "lks4NGm-4L",
      "to_id": "yF30wtD4Zp",
      "from_text": "за исключением случаев, предусмотренных настоящим Кодексом",
      "to_text": "Перевод работника на другую работу допускается с согласия работника, оформляется внесением соответствующих изменений в трудовой договор и актом работодателя",
      "from_label": "exceptions:ИСКЛЮЧЕНИЕ_ОБЩЕЕ",
      "to_label": "norm_structure:ДИСПОЗИЦИЯ",
      "relation": "ИСКЛЮЧАЕТ",
      "source": "auto",
      "confidence": 0.8,
      "trigger_phrase": "за исключением случаев, предусмотренных",
      "algorithm": "ALGO_ИСКЛЮЧАЕТ_v1",
      "expert_verdict": null,
      "expert_correction": null,
      "expert_comment": null
    },
    {
      "id": "REL_0008",
      "from_id": "ZlyZ20oueN",
      "to_id": "gMwA7LnFLj",
      "from_text": "поручение иной работы",
      "to_text": "размер заработной платы",
      "from_label": "action_type:ДЕЙСТВИЕ_АКТИВНОЕ",
      "to_label": "amounts:СУММА_ДЕНЬГИ",
      "relation": "ИМЕЕТ_МЕРУ",
      "source": "auto",
      "confidence": 0.767,
      "trigger_phrase": "рой изменяются условия труда (",
      "algorithm": "ALGO_ИМЕЕТ_МЕРУ_v1",
      "expert_verdict": null,
      "expert_correction": null,
      "expert_comment": null
    },
    {
      "id": "REL_0009",
      "from_id": "ZlyZ20oueN",
      "to_id": "Ml493GRMar",
      "from_text": "поручение иной работы",
      "to_text": "режим рабочего времени и времени отдыха",
      "from_label": "action_type:ДЕЙСТВИЕ_АКТИВНОЕ",
      "to_label": "temporal:ВРЕМЯ_ПЕРИОД",
      "relation": "ИМЕЕТ_МЕРУ",
      "source": "auto",
      "confidence": 0.692,
      "trigger_phrase": "руда (размер заработной платы,",
      "algorithm": "ALGO_ИМЕЕТ_МЕРУ_v1",
      "expert_verdict": null,
      "expert_correction": null,
      "expert_comment": null
    },
    {
      "id": "REL_0010",
      "from_id": "96UBrYDplO",
      "to_id": "BJnQvz_sre",
      "from_text": "1) изменение работы (трудовой функции) работника, то есть выполнение работы по другой должности, специальности, профессии, квалификации;\\n2) поручение иной работы, при выполнении которой изменяются условия труда (размер заработной платы, режим рабочего времени и времени отдыха, льготы и другие условия), обусловленные трудовым договором;\\n3) перевод в обособленное структурное подразделение работодателя;\\n4) перевод в другую местность вместе с работодателем",
      "to_text": "Переводом работника на другую работу является",
      "from_label": "norm_structure:ДИСПОЗИЦИЯ",
      "to_label": "norm_structure:ГИПОТЕЗА",
      "relation": "ИМЕЕТ_УСЛОВИЕ",
      "source": "auto",
      "confidence": 0.88,
      "trigger_phrase": "(hypothesis in same norm)",
      "algorithm": "ALGO_ИМЕЕТ_УСЛОВИЕ_v1",
      "expert_verdict": null,
      "expert_correction": null,
      "expert_comment": null
    },
    {
      "id": "REL_0011",
      "from_id": "96UBrYDplO",
      "to_id": "_eC0x02tlR",
      "from_text": "1) изменение работы (трудовой функции) работника, то есть выполнение работы по другой должности, специальности, профессии, квалификации;\\n2) поручение иной работы, при выполнении которой изменяются условия труда (размер заработной платы, режим рабочего времени и времени отдыха, льготы и другие условия), обусловленные трудовым договором;\\n3) перевод в обособленное структурное подразделение работодателя;\\n4) перевод в другую местность вместе с работодателем",
      "to_text": "при выполнении которой изменяются условия труда",
      "from_label": "norm_structure:ДИСПОЗИЦИЯ",
      "to_label": "conditions:УСЛОВИЕ_ЕСЛИ",
      "relation": "ИМЕЕТ_УСЛОВИЕ",
      "source": "auto",
      "confidence": 0.85,
      "trigger_phrase": "при выполнении которой изменяю",
      "algorithm": "ALGO_ИМЕЕТ_УСЛОВИЕ_v1",
      "expert_verdict": null,
      "expert_correction": null,
      "expert_comment": null
    },
    {
      "id": "REL_0012",
      "from_id": "_Dye86TvD1",
      "to_id": "_eC0x02tlR",
      "from_text": "Переводом работника на другую работу является:\\n1) изменение работы (трудовой функции) работника, то есть выполнение работы по другой должности, специальности, профессии, квалификации;\\n2) поручение иной работы, при выполнении которой изменяются условия труда (размер заработной платы, режим рабочего времени и времени отдыха, льготы и другие условия), обусловленные трудовым договором;\\n3) перевод в обособленное структурное подразделение работодателя;\\n4) перевод в другую местность вместе с работодателем",
      "to_text": "при выполнении которой изменяются условия труда",
      "from_label": "norm_types:НОРМА_ДЕФИНИТИВНАЯ",
      "to_label": "conditions:УСЛОВИЕ_ЕСЛИ",
      "relation": "ИМЕЕТ_УСЛОВИЕ",
      "source": "auto",
      "confidence": 0.85,
      "trigger_phrase": "при выполнении которой изменяю",
      "algorithm": "ALGO_ИМЕЕТ_УСЛОВИЕ_v1",
      "expert_verdict": null,
      "expert_correction": null,
      "expert_comment": null
    },
    {
      "id": "REL_0013",
      "from_id": "96UBrYDplO",
      "to_id": "iS0qK7qWQX",
      "from_text": "1) изменение работы (трудовой функции) работника, то есть выполнение работы по другой должности, специальности, профессии, квалификации;\\n2) поручение иной работы, при выполнении которой изменяются условия труда (размер заработной платы, режим рабочего времени и времени отдыха, льготы и другие условия), обусловленные трудовым договором;\\n3) перевод в обособленное структурное подразделение работодателя;\\n4) перевод в другую местность вместе с работодателем",
      "to_text": "в обособленное структурное подразделение работодателя",
      "from_label": "norm_structure:ДИСПОЗИЦИЯ",
      "to_label": "conditions:УСЛОВИЕ_ГДЕ",
      "relation": "ИМЕЕТ_УСЛОВИЕ",
      "source": "auto",
      "confidence": 0.85,
      "trigger_phrase": "в обособленное структурное под",
      "algorithm": "ALGO_ИМЕЕТ_УСЛОВИЕ_v1",
      "expert_verdict": null,
      "expert_correction": null,
      "expert_comment": null
    },
    {
      "id": "REL_0014",
      "from_id": "_Dye86TvD1",
      "to_id": "iS0qK7qWQX",
      "from_text": "Переводом работника на другую работу является:\\n1) изменение работы (трудовой функции) работника, то есть выполнение работы по другой должности, специальности, профессии, квалификации;\\n2) поручение иной работы, при выполнении которой изменяются условия труда (размер заработной платы, режим рабочего времени и времени отдыха, льготы и другие условия), обусловленные трудовым договором;\\n3) перевод в обособленное структурное подразделение работодателя;\\n4) перевод в другую местность вместе с работодателем",
      "to_text": "в обособленное структурное подразделение работодателя",
      "from_label": "norm_types:НОРМА_ДЕФИНИТИВНАЯ",
      "to_label": "conditions:УСЛОВИЕ_ГДЕ",
      "relation": "ИМЕЕТ_УСЛОВИЕ",
      "source": "auto",
      "confidence": 0.85,
      "trigger_phrase": "в обособленное структурное под",
      "algorithm": "ALGO_ИМЕЕТ_УСЛОВИЕ_v1",
      "expert_verdict": null,
      "expert_correction": null,
      "expert_comment": null
    },
    {
      "id": "REL_0015",
      "from_id": "96UBrYDplO",
      "to_id": "fPwLxbCG9Y",
      "from_text": "1) изменение работы (трудовой функции) работника, то есть выполнение работы по другой должности, специальности, профессии, квалификации;\\n2) поручение иной работы, при выполнении которой изменяются условия труда (размер заработной платы, режим рабочего времени и времени отдыха, льготы и другие условия), обусловленные трудовым договором;\\n3) перевод в обособленное структурное подразделение работодателя;\\n4) перевод в другую местность вместе с работодателем",
      "to_text": "в другую местность вместе с работодателем",
      "from_label": "norm_structure:ДИСПОЗИЦИЯ",
      "to_label": "conditions:УСЛОВИЕ_ГДЕ",
      "relation": "ИМЕЕТ_УСЛОВИЕ",
      "source": "auto",
      "confidence": 0.85,
      "trigger_phrase": "в другую местность вместе с ра",
      "algorithm": "ALGO_ИМЕЕТ_УСЛОВИЕ_v1",
      "expert_verdict": null,
      "expert_correction": null,
      "expert_comment": null
    },
    {
      "id": "REL_0016",
      "from_id": "_Dye86TvD1",
      "to_id": "fPwLxbCG9Y",
      "from_text": "Переводом работника на другую работу является:\\n1) изменение работы (трудовой функции) работника, то есть выполнение работы по другой должности, специальности, профессии, квалификации;\\n2) поручение иной работы, при выполнении которой изменяются условия труда (размер заработной платы, режим рабочего времени и времени отдыха, льготы и другие условия), обусловленные трудовым договором;\\n3) перевод в обособленное структурное подразделение работодателя;\\n4) перевод в другую местность вместе с работодателем",
      "to_text": "в другую местность вместе с работодателем",
      "from_label": "norm_types:НОРМА_ДЕФИНИТИВНАЯ",
      "to_label": "conditions:УСЛОВИЕ_ГДЕ",
      "relation": "ИМЕЕТ_УСЛОВИЕ",
      "source": "auto",
      "confidence": 0.85,
      "trigger_phrase": "в другую местность вместе с ра",
      "algorithm": "ALGO_ИМЕЕТ_УСЛОВИЕ_v1",
      "expert_verdict": null,
      "expert_correction": null,
      "expert_comment": null
    },
    {
      "id": "REL_0017",
      "from_id": "yF30wtD4Zp",
      "to_id": "awKPSU3TiP",
      "from_text": "Перевод работника на другую работу допускается с согласия работника, оформляется внесением соответствующих изменений в трудовой договор и актом работодателя",
      "to_text": "за исключением случаев, предусмотренных настоящим Кодексом",
      "from_label": "norm_structure:ДИСПОЗИЦИЯ",
      "to_label": "norm_structure:ГИПОТЕЗА",
      "relation": "ИМЕЕТ_УСЛОВИЕ",
      "source": "auto",
      "confidence": 0.88,
      "trigger_phrase": "(hypothesis in same norm)",
      "algorithm": "ALGO_ИМЕЕТ_УСЛОВИЕ_v1",
      "expert_verdict": null,
      "expert_correction": null,
      "expert_comment": null
    },
    {
      "id": "REL_0018",
      "from_id": "OhvOEd0OZK",
      "to_id": "OWU--0YVgb",
      "from_text": "Не допускается перевод работника на другую работу",
      "to_text": "при противопоказаниях для работника по состоянию здоровья, подтвержденных медицинским заключением",
      "from_label": "norm_structure:ДИСПОЗИЦИЯ",
      "to_label": "norm_structure:ГИПОТЕЗА",
      "relation": "ИМЕЕТ_УСЛОВИЕ",
      "source": "auto",
      "confidence": 0.88,
      "trigger_phrase": "(hypothesis in same norm)",
      "algorithm": "ALGO_ИМЕЕТ_УСЛОВИЕ_v1",
      "expert_verdict": null,
      "expert_correction": null,
      "expert_comment": null
    },
    {
      "id": "REL_0019",
      "from_id": "i_v5WwQeg5",
      "to_id": "QHpi8AoUaM",
      "from_text": "работника",
      "to_text": "допускается",
      "from_label": "legal_subject:СУБЪЕКТ_ФИЗЛИЦО",
      "to_label": "action_modality:ДЕЙСТВИЕ_ПРАВО",
      "relation": "СОВЕРШАЕТ",
      "source": "auto",
      "confidence": 0.878,
      "trigger_phrase": "(adjacent, active voice)",
      "algorithm": "ALGO_СОВЕРШАЕТ_v1",
      "expert_verdict": null,
      "expert_correction": null,
      "expert_comment": null
    },
    {
      "id": "REL_0020",
      "from_id": "fZDFXhJ8NW",
      "to_id": "TKX2IbyAFK",
      "from_text": "работника",
      "to_text": "оформляется внесением соответствующих изменений в трудовой договор и актом работодателя",
      "from_label": "legal_subject:СУБЪЕКТ_ФИЗЛИЦО",
      "to_label": "action_type:ДЕЙСТВИЕ_ПРОЦЕДУРНОЕ",
      "relation": "СОВЕРШАЕТ",
      "source": "auto",
      "confidence": 0.942,
      "trigger_phrase": "(adjacent, active voice)",
      "algorithm": "ALGO_СОВЕРШАЕТ_v1",
      "expert_verdict": null,
      "expert_correction": null,
      "expert_comment": null
    },
    {
      "id": "REL_0021",
      "from_id": "m1dhAZP_gK",
      "to_id": "ptYUt-SNQ1",
      "from_text": "Не допускается перевод работника на другую работу",
      "to_text": "подтвержденных медицинским заключением",
      "from_label": "action_modality:ДЕЙСТВИЕ_ЗАПРЕТ",
      "to_label": "legal_objects:ОБЪЕКТ_ДОКУМЕНТ",
      "relation": "НАПРАВЛЕНО_НА",
      "source": "auto",
      "confidence": 0.72,
      "trigger_phrase": "(direct object)",
      "algorithm": "ALGO_НАПРАВЛЕНО_НА_v1",
      "expert_verdict": null,
      "expert_correction": null,
      "expert_comment": null
    },
    {
      "id": "REL_0022",
      "from_id": "64rVor3CFs",
      "to_id": "ptYUt-SNQ1",
      "from_text": "перевод работника на другую работу",
      "to_text": "подтвержденных медицинским заключением",
      "from_label": "action_type:ДЕЙСТВИЕ_ПРОЦЕДУРНОЕ",
      "to_label": "legal_objects:ОБЪЕКТ_ДОКУМЕНТ",
      "relation": "НАПРАВЛЕНО_НА",
      "source": "auto",
      "confidence": 0.72,
      "trigger_phrase": "(direct object)",
      "algorithm": "ALGO_НАПРАВЛЕНО_НА_v1",
      "expert_verdict": null,
      "expert_correction": null,
      "expert_comment": null
    },
    {
      "id": "REL_0023",
      "from_id": "i5X8r9FFnn",
      "to_id": "ptYUt-SNQ1",
      "from_text": "по состоянию здоровья",
      "to_text": "подтвержденных медицинским заключением",
      "from_label": "action_modality:ДЕЙСТВИЕ_ПРАВО",
      "to_label": "legal_objects:ОБЪЕКТ_ДОКУМЕНТ",
      "relation": "НАПРАВЛЕНО_НА",
      "source": "auto",
      "confidence": 0.894,
      "trigger_phrase": "(direct object)",
      "algorithm": "ALGO_НАПРАВЛЕНО_НА_v1",
      "expert_verdict": null,
      "expert_correction": null,
      "expert_comment": null
    },
    {
      "id": "REL_0024",
      "from_id": "_Dye86TvD1",
      "to_id": "BJnQvz_sre",
      "from_text": "Переводом работника на другую работу является:\\n1) изменение работы (трудовой функции) работника, то есть выполнение работы по другой должности, специальности, профессии, квалификации;\\n2) поручение иной работы, при выполнении которой изменяются условия труда (размер заработной платы, режим рабочего времени и времени отдыха, льготы и другие условия), обусловленные трудовым договором;\\n3) перевод в обособленное структурное подразделение работодателя;\\n4) перевод в другую местность вместе с работодателем",
      "to_text": "Переводом работника на другую работу является",
      "from_label": "norm_types:НОРМА_ДЕФИНИТИВНАЯ",
      "to_label": "norm_structure:ГИПОТЕЗА",
      "relation": "СОСТОИТ_ИЗ",
      "source": "auto",
      "confidence": 0.98,
      "trigger_phrase": "(norm_structure inside norm)",
      "algorithm": "ALGO_СОСТОИТ_ИЗ_v1",
      "expert_verdict": null,
      "expert_correction": null,
      "expert_comment": null
    },
    {
      "id": "REL_0025",
      "from_id": "_Dye86TvD1",
      "to_id": "96UBrYDplO",
      "from_text": "Переводом работника на другую работу является:\\n1) изменение работы (трудовой функции) работника, то есть выполнение работы по другой должности, специальности, профессии, квалификации;\\n2) поручение иной работы, при выполнении которой изменяются условия труда (размер заработной платы, режим рабочего времени и времени отдыха, льготы и другие условия), обусловленные трудовым договором;\\n3) перевод в обособленное структурное подразделение работодателя;\\n4) перевод в другую местность вместе с работодателем",
      "to_text": "1) изменение работы (трудовой функции) работника, то есть выполнение работы по другой должности, специальности, профессии, квалификации;\\n2) поручение иной работы, при выполнении которой изменяются условия труда (размер заработной платы, режим рабочего времени и времени отдыха, льготы и другие условия), обусловленные трудовым договором;\\n3) перевод в обособленное структурное подразделение работодателя;\\n4) перевод в другую местность вместе с работодателем",
      "from_label": "norm_types:НОРМА_ДЕФИНИТИВНАЯ",
      "to_label": "norm_structure:ДИСПОЗИЦИЯ",
      "relation": "СОСТОИТ_ИЗ",
      "source": "auto",
      "confidence": 0.98,
      "trigger_phrase": "(norm_structure inside norm)",
      "algorithm": "ALGO_СОСТОИТ_ИЗ_v1",
      "expert_verdict": null,
      "expert_correction": null,
      "expert_comment": null
    },
    {
      "id": "REL_0026",
      "from_id": "yuwZCuRiLz",
      "to_id": "awKPSU3TiP",
      "from_text": "Перевод работника на другую работу допускается с согласия работника, оформляется внесением соответствующих изменений в трудовой договор и актом работодателя, за исключением случаев, предусмотренных настоящим Кодексом",
      "to_text": "за исключением случаев, предусмотренных настоящим Кодексом",
      "from_label": "norm_types:НОРМА_УПРАВОМОЧИВАЮЩАЯ",
      "to_label": "norm_structure:ГИПОТЕЗА",
      "relation": "СОСТОИТ_ИЗ",
      "source": "auto",
      "confidence": 0.98,
      "trigger_phrase": "(norm_structure inside norm)",
      "algorithm": "ALGO_СОСТОИТ_ИЗ_v1",
      "expert_verdict": null,
      "expert_correction": null,
      "expert_comment": null
    },
    {
      "id": "REL_0027",
      "from_id": "yuwZCuRiLz",
      "to_id": "yF30wtD4Zp",
      "from_text": "Перевод работника на другую работу допускается с согласия работника, оформляется внесением соответствующих изменений в трудовой договор и актом работодателя, за исключением случаев, предусмотренных настоящим Кодексом",
      "to_text": "Перевод работника на другую работу допускается с согласия работника, оформляется внесением соответствующих изменений в трудовой договор и актом работодателя",
      "from_label": "norm_types:НОРМА_УПРАВОМОЧИВАЮЩАЯ",
      "to_label": "norm_structure:ДИСПОЗИЦИЯ",
      "relation": "СОСТОИТ_ИЗ",
      "source": "auto",
      "confidence": 0.98,
      "trigger_phrase": "(norm_structure inside norm)",
      "algorithm": "ALGO_СОСТОИТ_ИЗ_v1",
      "expert_verdict": null,
      "expert_correction": null,
      "expert_comment": null
    },
    {
      "id": "REL_0028",
      "from_id": "iJYnZP02mw",
      "to_id": "OWU--0YVgb",
      "from_text": "Не допускается перевод работника на другую работу при противопоказаниях для работника по состоянию здоровья, подтвержденных медицинским заключением",
      "to_text": "при противопоказаниях для работника по состоянию здоровья, подтвержденных медицинским заключением",
      "from_label": "norm_types:НОРМА_ЗАПРЕЩАЮЩАЯ",
      "to_label": "norm_structure:ГИПОТЕЗА",
      "relation": "СОСТОИТ_ИЗ",
      "source": "auto",
      "confidence": 0.98,
      "trigger_phrase": "(norm_structure inside norm)",
      "algorithm": "ALGO_СОСТОИТ_ИЗ_v1",
      "expert_verdict": null,
      "expert_correction": null,
      "expert_comment": null
    },
    {
      "id": "REL_0029",
      "from_id": "iJYnZP02mw",
      "to_id": "OhvOEd0OZK",
      "from_text": "Не допускается перевод работника на другую работу при противопоказаниях для работника по состоянию здоровья, подтвержденных медицинским заключением",
      "to_text": "Не допускается перевод работника на другую работу",
      "from_label": "norm_types:НОРМА_ЗАПРЕЩАЮЩАЯ",
      "to_label": "norm_structure:ДИСПОЗИЦИЯ",
      "relation": "СОСТОИТ_ИЗ",
      "source": "auto",
      "confidence": 0.98,
      "trigger_phrase": "(norm_structure inside norm)",
      "algorithm": "ALGO_СОСТОИТ_ИЗ_v1",
      "expert_verdict": null,
      "expert_correction": null,
      "expert_comment": null
    }
  ],
  "expert_additions": []
}